{
  "schemaVersion": "1.0.0",
  "id": 66003,
  "name": "Loam Maintenance",
  "expansion": "arr",
  "category": "msq",
  "enabled": true,
  "supportStatus": {
    "implementation": "partial",
    "knownIssues": [],
    "minigameSkippable": null
  },
  "lastVerifiedPatch": "unknown",
  "requirements": {
    "minLevel": 5,
    "maxLevel": null,
    "requiredJob": null,
    "requiredStartingClass": null,
    "prereqs": []
  },
  "acceptFrom": {
    "npcId": 1002627,
    "zone": 134,
    "position": {
      "x": 203.32642,
      "y": 111.7238,
      "z": -213.91626
    }
  },
  "chain": null,
  "rewardOverride": null,
  "contributors": null,
  "notes": null,
  "sequences": [
    {
      "sequence": 0,
      "skipIf": null,
      "steps": [
        {
          "type": "accept",
          "target": {
            "npcId": 1002627,
            "zone": 134,
            "position": {
              "x": 203.32642,
              "y": 111.7238,
              "z": -213.91626
            }
          },
          "id": "accept-quest",
          "zone": "134",
          "requiredZone": "134",
          "resumePointFragmentId": null,
          "expect": "isQuestAccepted(66003)",
          "skipIf": null,
          "stopDistance": null,
          "recover": null,
          "retry": null,
          "preconditions": null,
          "notes": null
        }
      ]
    },
    {
      "sequence": 1,
      "skipIf": null,
      "steps": [
        {
          "type": "talk",
          "target": {
            "npcId": 1002629,
            "zone": 134,
            "position": {
              "x": 52.750366,
              "y": 64.48143,
              "z": -185.71759
            }
          },
          "targets": null,
          "targetOrder": null,
          "dialogueChoices": [],
          "id": "talk-to-npc-1002629",
          "zone": "134",
          "requiredZone": "134",
          "resumePointFragmentId": null,
          "expect": "questSequence(66003) >= 2",
          "skipIf": null,
          "stopDistance": null,
          "recover": null,
          "retry": null,
          "preconditions": null,
          "notes": null
        }
      ]
    },
    {
      "sequence": 2,
      "skipIf": null,
      "steps": [
        {
          "type": "pickup-item",
          "interactableId": 2001237,
          "position": {
            "x": -129.38129,
            "y": 46.67737,
            "z": -192.52313
          },
          "id": "pickup-item-2000347",
          "zone": "134",
          "requiredZone": "134",
          "resumePointFragmentId": null,
          "expect": "playerHasItem(2000347)",
          "skipIf": null,
          "stopDistance": null,
          "recover": null,
          "retry": null,
          "preconditions": null,
          "notes": null
        },
        {
          "type": "interact-object",
          "interactableId": 2001238,
          "position": {
            "x": -121.78229,
            "y": 45.97534,
            "z": -210.83392
          },
          "id": "interact-object-2001238",
          "zone": "134",
          "requiredZone": "134",
          "resumePointFragmentId": null,
          "expect": "questVariableHigh(66003, 0) >= 2",
          "skipIf": null,
          "stopDistance": null,
          "recover": null,
          "retry": null,
          "preconditions": null,
          "notes": null
        },
        {
          "type": "interact-object",
          "interactableId": 2001239,
          "position": {
            "x": -132.9519,
            "y": 45.365112,
            "z": -228.93109
          },
          "id": "interact-object-2001239",
          "zone": "134",
          "requiredZone": "134",
          "resumePointFragmentId": null,
          "expect": "questSequence(66003) >= 255",
          "skipIf": null,
          "stopDistance": null,
          "recover": null,
          "retry": null,
          "preconditions": null,
          "notes": null
        }
      ]
    },
    {
      "sequence": 255,
      "skipIf": null,
      "steps": [
        {
          "type": "turn-in",
          "target": {
            "npcId": 1002631,
            "zone": 134,
            "position": {
              "x": 0.045776367,
              "y": 57.85028,
              "z": -308.76636
            }
          },
          "dialogueChoices": [],
          "id": "turn-in-quest",
          "zone": "134",
          "requiredZone": "134",
          "resumePointFragmentId": null,
          "expect": "isQuestComplete(66003)",
          "skipIf": null,
          "stopDistance": null,
          "recover": null,
          "retry": null,
          "preconditions": null,
          "notes": null
        }
      ]
    }
  ]
}